biomapy/__init__.py
biomapy/biomapy.py
biomapy/datasets/HUMAN_9606_idmapping.dat.gz
biomapy/datasets/Homo_sapiens.gene_info.gz
biomapy-0.3.3.dist-info/LICENSE.txt
biomapy-0.3.3.dist-info/METADATA
biomapy-0.3.3.dist-info/WHEEL
biomapy-0.3.3.dist-info/top_level.txt
biomapy-0.3.3.dist-info/RECORD
