Metadata-Version: 2.1
Name: biomapy
Version: 0.3.3
Author: Francesco Gualdi
License: GPL
License-File: LICENSE.txt
Requires-Dist: wget
Requires-Dist: requests
